PandasUtils/__init__.py
PandasUtils/utils.py
jason_pandas-1.0.2.dist-info/METADATA
jason_pandas-1.0.2.dist-info/WHEEL
jason_pandas-1.0.2.dist-info/top_level.txt
jason_pandas-1.0.2.dist-info/RECORD
