Metadata-Version: 2.1
Name: jason-pandas
Version: 1.0.2
Summary: Pandas is a very popular data processing library that provides a wealth of functions and methods that can be used for data cleaning, analysis, and visualization tasks. By wrapping these functions, your project makes the process of using pandas more convenient, helping people to quickly complete data processing tasks.
Home-page: UNKNOWN
Author: Jason
Author-email: jasonforjob@qq.com
License: MIT
Platform: UNKNOWN
Requires-Dist: numpy
Requires-Dist: pandas
